pyairview.py
pyairview-0.1a2.data/scripts/pyairview_test.py
pyairview-0.1a2.dist-info/DESCRIPTION.rst
pyairview-0.1a2.dist-info/METADATA
pyairview-0.1a2.dist-info/metadata.json
pyairview-0.1a2.dist-info/RECORD
pyairview-0.1a2.dist-info/top_level.txt
pyairview-0.1a2.dist-info/WHEEL
