Metadata-Version: 2.0
Name: pyairview
Version: 0.1a2
Summary: PyAirview is a very simple Python library for the Ubiquiti Airview2 2.4GHz spectrum analyzer, which has an undocumented device API.
Home-page: http://infincia.github.io/pyairview/
Author: Stephen Oliver
Author-email: steve@infincia.com
License: MIT
Keywords: airview ubiquiti airview2 spectrum analyzer
Platform: any
Classifier: Development Status :: 3 - Alpha
Classifier: License :: OSI Approved :: MIT License
Classifier: Natural Language :: English
Classifier: Operating System :: MacOS :: MacOS X
Classifier: Operating System :: Microsoft :: Windows
Classifier: Operating System :: POSIX
Classifier: Programming Language :: Python :: 2.7
Classifier: Programming Language :: Python :: 3.2
Classifier: Programming Language :: Python :: 3.3
Classifier: Programming Language :: Python :: 3.4
Classifier: Topic :: Software Development :: Libraries
Classifier: Topic :: Software Development :: Libraries :: Python Modules
Classifier: Topic :: System :: Hardware :: Hardware Drivers
Requires-Dist: PySerial
